{
    "results": {
        "id": "*UNKNOWN*",
        "processed_lang": "en",
        "source": "*UNKNOWN*",
        "tree": {
            "children": [
                {
                    "children": [
                        {
                            "category": "personality",
                            "children": [
                                {
                                    "category": "personality",
                                    "children": [
                                        {
                                            "category": "personality",
                                            "id": "Adventurousness",
                                            "name": "Adventurousness",
                                            "percentage": 0.7545442656228794,
                                            "sampling_error": 0.04503803448
                    },
                                        {
                                            "category": "personality",
                                            "id": "Artistic interests",
                                            "name": "Artistic interests",
                                            "percentage": 0.225502760141836,
                                            "sampling_error": 0.09166406224
                    },
                                        {
                                            "category": "personality",
                                            "id": "Emotionality",
                                            "name": "Emotionality",
                                            "percentage": 0.24523108485254996,
                                            "sampling_error": 0.042016557999999996
                    },
                                        {
                                            "category": "personality",
                                            "id": "Imagination",
                                            "name": "Imagination",
                                            "percentage": 0.9268967726296888,
                                            "sampling_error": 0.05568118056
                    },
                                        {
                                            "category": "personality",
                                            "id": "Intellect",
                                            "name": "Intellect",
                                            "percentage": 0.7659086475185519,
                                            "sampling_error": 0.04844262344
                    },
                                        {
                                            "category": "personality",
                                            "id": "Liberalism",
                                            "name": "Authority-challenging",
                                            "percentage": 0.7334381477257015,
                                            "sampling_error": 0.07431388376
                    }
                  ],
                                    "id": "Openness",
                                    "name": "Openness",
                                    "percentage": 0.8215908035993171,
                                    "sampling_error": 0.0510229112
                },
                                {
                                    "category": "personality",
                                    "children": [
                                        {
                                            "category": "personality",
                                            "id": "Achievement striving",
                                            "name": "Achievement striving",
                                            "percentage": 0.34322275007660896,
                                            "sampling_error": 0.0874736992
                    },
                                        {
                                            "category": "personality",
                                            "id": "Cautiousness",
                                            "name": "Cautiousness",
                                            "percentage": 0.2361314135031104,
                                            "sampling_error": 0.08193561760000001
                    },
                                        {
                                            "category": "personality",
                                            "id": "Dutifulness",
                                            "name": "Dutifulness",
                                            "percentage": 0.04490838234078218,
                                            "sampling_error": 0.05392249592
                    },
                                        {
                                            "category": "personality",
                                            "id": "Orderliness",
                                            "name": "Orderliness",
                                            "percentage": 0.07484348313197248,
                                            "sampling_error": 0.06202816568
                    },
                                        {
                                            "category": "personality",
                                            "id": "Self-discipline",
                                            "name": "Self-discipline",
                                            "percentage": 0.4940512248517862,
                                            "sampling_error": 0.04156405472
                    },
                                        {
                                            "category": "personality",
                                            "id": "Self-efficacy",
                                            "name": "Self-efficacy",
                                            "percentage": 0.24289487529328896,
                                            "sampling_error": 0.08073146824
                    }
                  ],
                                    "id": "Conscientiousness",
                                    "name": "Conscientiousness",
                                    "percentage": 0.5339014575805956,
                                    "sampling_error": 0.06508407792
                },
                                {
                                    "category": "personality",
                                    "children": [
                                        {
                                            "category": "personality",
                                            "id": "Activity level",
                                            "name": "Activity level",
                                            "percentage": 0.009437623008140893,
                                            "sampling_error": 0.06809309928
                    },
                                        {
                                            "category": "personality",
                                            "id": "Assertiveness",
                                            "name": "Assertiveness",
                                            "percentage": 0.7146225688787656,
                                            "sampling_error": 0.07213947304
                    },
                                        {
                                            "category": "personality",
                                            "id": "Cheerfulness",
                                            "name": "Cheerfulness",
                                            "percentage": 0.18303587911160632,
                                            "sampling_error": 0.09072920784
                    },
                                        {
                                            "category": "personality",
                                            "id": "Excitement-seeking",
                                            "name": "Excitement-seeking",
                                            "percentage": 0.4177707731757391,
                                            "sampling_error": 0.07395156384
                    },
                                        {
                                            "category": "personality",
                                            "id": "Friendliness",
                                            "name": "Outgoing",
                                            "percentage": 0.05590052227593706,
                                            "sampling_error": 0.06649452992
                    },
                                        {
                                            "category": "personality",
                                            "id": "Gregariousness",
                                            "name": "Gregariousness",
                                            "percentage": 0.09081586510206603,
                                            "sampling_error": 0.05161286056
                    }
                  ],
                                    "id": "Extraversion",
                                    "name": "Extraversion",
                                    "percentage": 0.5351190857457084,
                                    "sampling_error": 0.04889980952
                },
                                {
                                    "category": "personality",
                                    "children": [
                                        {
                                            "category": "personality",
                                            "id": "Altruism",
                                            "name": "Altruism",
                                            "percentage": 0.029515173827073707,
                                            "sampling_error": 0.06212326336
                    },
                                        {
                                            "category": "personality",
                                            "id": "Cooperation",
                                            "name": "Cooperation",
                                            "percentage": 0.04284761839283712,
                                            "sampling_error": 0.07194976128000001
                    },
                                        {
                                            "category": "personality",
                                            "id": "Modesty",
                                            "name": "Modesty",
                                            "percentage": 0.01928655973235672,
                                            "sampling_error": 0.04759148352
                    },
                                        {
                                            "category": "personality",
                                            "id": "Morality",
                                            "name": "Uncompromising",
                                            "percentage": 0.014672720029872943,
                                            "sampling_error": 0.05540643656
                    },
                                        {
                                            "category": "personality",
                                            "id": "Sympathy",
                                            "name": "Sympathy",
                                            "percentage": 0.05356815327854603,
                                            "sampling_error": 0.0858331708
                    },
                                        {
                                            "category": "personality",
                                            "id": "Trust",
                                            "name": "Trust",
                                            "percentage": 0.011658762154760095,
                                            "sampling_error": 0.048610904079999996
                    }
                  ],
                                    "id": "Agreeableness",
                                    "name": "Agreeableness",
                                    "percentage": 0.05891382301288661,
                                    "sampling_error": 0.08599793704
                },
                                {
                                    "category": "personality",
                                    "children": [
                                        {
                                            "category": "personality",
                                            "id": "Anger",
                                            "name": "Fiery",
                                            "percentage": 0.239331898855951,
                                            "sampling_error": 0.08237623472
                    },
                                        {
                                            "category": "personality",
                                            "id": "Anxiety",
                                            "name": "Prone to worry",
                                            "percentage": 0.2454104863782632,
                                            "sampling_error": 0.04761528032
                    },
                                        {
                                            "category": "personality",
                                            "id": "Depression",
                                            "name": "Melancholy",
                                            "percentage": 0.4094873215057957,
                                            "sampling_error": 0.049720978
                    },
                                        {
                                            "category": "personality",
                                            "id": "Immoderation",
                                            "name": "Immoderation",
                                            "percentage": 0.42077477659568147,
                                            "sampling_error": 0.04661664104
                    },
                                        {
                                            "category": "personality",
                                            "id": "Self-consciousness",
                                            "name": "Self-consciousness",
                                            "percentage": 0.05641398185967467,
                                            "sampling_error": 0.04888743976
                    },
                                        {
                                            "category": "personality",
                                            "id": "Vulnerability",
                                            "name": "Susceptible to stress",
                                            "percentage": 0.18134369386679247,
                                            "sampling_error": 0.07409009232
                    }
                  ],
                                    "id": "Neuroticism",
                                    "name": "Emotional range",
                                    "percentage": 0.22685283568157136,
                                    "sampling_error": 0.07835914583999999
                }
              ],
                            "id": "Agreeableness_parent",
                            "name": "Agreeableness",
                            "percentage": 0.05891382301288661
            }
          ],
                    "id": "personality",
                    "name": "Big 5"
        },
                {
                    "children": [
                        {
                            "category": "needs",
                            "children": [
                                {
                                    "category": "needs",
                                    "id": "Challenge",
                                    "name": "Challenge",
                                    "percentage": 0.3393060655502773,
                                    "sampling_error": 0.07317361464
                },
                                {
                                    "category": "needs",
                                    "id": "Closeness",
                                    "name": "Closeness",
                                    "percentage": 0.3189092301908306,
                                    "sampling_error": 0.072547504
                },
                                {
                                    "category": "needs",
                                    "id": "Curiosity",
                                    "name": "Curiosity",
                                    "percentage": 0.6352960648557833,
                                    "sampling_error": 0.10245288912
                },
                                {
                                    "category": "needs",
                                    "id": "Excitement",
                                    "name": "Excitement",
                                    "percentage": 0.25789888830737845,
                                    "sampling_error": 0.09270605456
                },
                                {
                                    "category": "needs",
                                    "id": "Harmony",
                                    "name": "Harmony",
                                    "percentage": 0.04030812449343812,
                                    "sampling_error": 0.09218552304
                },
                                {
                                    "category": "needs",
                                    "id": "Ideal",
                                    "name": "Ideal",
                                    "percentage": 0.8256945297354155,
                                    "sampling_error": 0.08355973848
                },
                                {
                                    "category": "needs",
                                    "id": "Liberty",
                                    "name": "Liberty",
                                    "percentage": 0.16684068100432894,
                                    "sampling_error": 0.12460757823999999
                },
                                {
                                    "category": "needs",
                                    "id": "Love",
                                    "name": "Love",
                                    "percentage": 0.023693328951407022,
                                    "sampling_error": 0.08486102448
                },
                                {
                                    "category": "needs",
                                    "id": "Practicality",
                                    "name": "Practicality",
                                    "percentage": 0.02740635265042133,
                                    "sampling_error": 0.07477748632
                },
                                {
                                    "category": "needs",
                                    "id": "Self-expression",
                                    "name": "Self-expression",
                                    "percentage": 0.3573723677493023,
                                    "sampling_error": 0.07162610912
                },
                                {
                                    "category": "needs",
                                    "id": "Stability",
                                    "name": "Stability",
                                    "percentage": 0.3727806344882726,
                                    "sampling_error": 0.09145601351999999
                },
                                {
                                    "category": "needs",
                                    "id": "Structure",
                                    "name": "Structure",
                                    "percentage": 0.13011060097519983,
                                    "sampling_error": 0.06934166872000001
                }
              ],
                            "id": "Love_parent",
                            "name": "Love",
                            "percentage": 0.023693328951407022
            }
          ],
                    "id": "needs",
                    "name": "Needs"
        },
                {
                    "children": [
                        {
                            "category": "values",
                            "children": [
                                {
                                    "category": "values",
                                    "id": "Conservation",
                                    "name": "Conservation",
                                    "percentage": 0.3810839471724897,
                                    "sampling_error": 0.061853662639999994
                },
                                {
                                    "category": "values",
                                    "id": "Openness to change",
                                    "name": "Openness to change",
                                    "percentage": 0.45515933247521706,
                                    "sampling_error": 0.056443610479999996
                },
                                {
                                    "category": "values",
                                    "id": "Hedonism",
                                    "name": "Hedonism",
                                    "percentage": 0.44943636304020507,
                                    "sampling_error": 0.11425543896
                },
                                {
                                    "category": "values",
                                    "id": "Self-enhancement",
                                    "name": "Self-enhancement",
                                    "percentage": 0.33028902295572493,
                                    "sampling_error": 0.0883798988
                },
                                {
                                    "category": "values",
                                    "id": "Self-transcendence",
                                    "name": "Self-transcendence",
                                    "percentage": 0.7779526922911439,
                                    "sampling_error": 0.06658221608
                }
              ],
                            "id": "Self-transcendence_parent",
                            "name": "Self-transcendence",
                            "percentage": 0.7779526922911439
            }
          ],
                    "id": "values",
                    "name": "Values"
        }
      ],
            "id": "r",
            "name": "root"
        },
        "word_count": 6216
    }
}